README.txt
setup.cfg
setup.py
collective/__init__.py
collective.wasthisuseful.egg-info/PKG-INFO
collective.wasthisuseful.egg-info/SOURCES.txt
collective.wasthisuseful.egg-info/dependency_links.txt
collective.wasthisuseful.egg-info/entry_points.txt
collective.wasthisuseful.egg-info/namespace_packages.txt
collective.wasthisuseful.egg-info/not-zip-safe
collective.wasthisuseful.egg-info/paster_plugins.txt
collective.wasthisuseful.egg-info/requires.txt
collective.wasthisuseful.egg-info/top_level.txt
collective/wasthisuseful/__init__.py
collective/wasthisuseful/adapters.py
collective/wasthisuseful/config.py
collective/wasthisuseful/configure.zcml
collective/wasthisuseful/event.py
collective/wasthisuseful/handlers.py
collective/wasthisuseful/interfaces.py
collective/wasthisuseful/permissions.zcml
collective/wasthisuseful/profiles.zcml
collective/wasthisuseful/rebuild_i18n.sh
collective/wasthisuseful/tests.py
collective/wasthisuseful/browser/__init__.py
collective/wasthisuseful/browser/configure.zcml
collective/wasthisuseful/browser/controlpanel.py
collective/wasthisuseful/browser/useful.pt
collective/wasthisuseful/browser/viewlets.py
collective/wasthisuseful/browser/images/controlpanel_icon.png
collective/wasthisuseful/browser/images/thumbs.png
collective/wasthisuseful/browser/javascripts/wasthisuseful.js
collective/wasthisuseful/browser/stylesheets/wasthisuseful.css
collective/wasthisuseful/browser/templates/settings.pt
collective/wasthisuseful/browser/views/__init__.py
collective/wasthisuseful/browser/views/formparser.py
collective/wasthisuseful/browser/views/settings.py
collective/wasthisuseful/locales/Makefile
collective/wasthisuseful/locales/collective.wasthisuseful.pot
collective/wasthisuseful/locales/nl/LC_MESSAGES/collective.wasthisuseful.po
collective/wasthisuseful/profiles/default/actions.xml
collective/wasthisuseful/profiles/default/browserlayer.xml
collective/wasthisuseful/profiles/default/controlpanel.xml
collective/wasthisuseful/profiles/default/cssregistry.xml
collective/wasthisuseful/profiles/default/jsregistry.xml
collective/wasthisuseful/profiles/default/metadata.xml
collective/wasthisuseful/profiles/default/registry.xml
collective/wasthisuseful/profiles/default/rolemap.xml
collective/wasthisuseful/profiles/default/viewlets.xml
docs/HISTORY.txt
docs/INSTALL.txt
docs/LICENSE.GPL
docs/LICENSE.txt