Metadata-Version: 1.0
Name: collective.wasthisuseful
Version: 1.0
Summary: Simple yes/no usefulness rating for Plone content, enables e-mail notification
Home-page: http://svn.plone.org/svn/collective/collective.wasthisuseful
Author: Kees Hink
Author-email: hink@gw20e.com
License: GPL
Keywords: plone rating useful e-mail
Platform: UNKNOWN
Classifier: Framework :: Plone
Classifier: Programming Language :: Python
